docinterrogator/DocInterrogator.py
docinterrogator/__init__.py
docinterrogator-0.1.0.dist-info/METADATA
docinterrogator-0.1.0.dist-info/WHEEL
docinterrogator-0.1.0.dist-info/RECORD
